tsql/__init__.py
tsql/tsql.py
tsqlite-0.2.1.dist-info/LICENSE
tsqlite-0.2.1.dist-info/METADATA
tsqlite-0.2.1.dist-info/WHEEL
tsqlite-0.2.1.dist-info/top_level.txt
tsqlite-0.2.1.dist-info/RECORD
