Metadata-Version: 2.1
Name: tsqlite
Version: 0.2.1
Summary: A Python library for managing and syncing SQLite databases over Telegram channels with secure encryption.
Home-page: https://github.com/sina8013/TSQL
Author: Sina Saeedi
Author-email: sina8013@gmail.com
Classifier: Development Status :: 4 - Beta
Classifier: Intended Audience :: Developers
Classifier: Topic :: Software Development :: Libraries
Classifier: Topic :: Database :: Database Engines/Servers
Classifier: Topic :: Communications :: Chat
Classifier: Programming Language :: Python :: 3
Classifier: Programming Language :: Python :: 3.6
Classifier: Programming Language :: Python :: 3.7
Classifier: Programming Language :: Python :: 3.8
Classifier: Programming Language :: Python :: 3.9
Classifier: Programming Language :: Python :: 3.10
Classifier: License :: OSI Approved :: MIT License
Classifier: Operating System :: OS Independent
Requires-Python: >=3.6
License-File: LICENSE
Requires-Dist: telethon >=1.24.0
Requires-Dist: pycryptodome >=3.15.0
Requires-Dist: pandas >=1.3.0
